visualpic/__init__.py
visualpic/helper_functions.py
visualpic/analysis/__init__.py
visualpic/analysis/beam_evolution.py
visualpic/cli/__init__.py
visualpic/cli/vpic.py
visualpic/cli/vpic3d.py
visualpic/data_handling/__init__.py
visualpic/data_handling/data_container.py
visualpic/data_handling/derived_field_definitions.py
visualpic/data_handling/derived_particle_data_definitions.py
visualpic/data_handling/fields.py
visualpic/data_handling/particle_species.py
visualpic/data_handling/unit_converters.py
visualpic/data_reading/__init__.py
visualpic/data_reading/field_readers.py
visualpic/data_reading/folder_scanners.py
visualpic/data_reading/openpmd_data_reader.py
visualpic/data_reading/particle_readers.py
visualpic/ui/__init__.py
visualpic/ui/basic_plot_window.py
visualpic/ui/basic_render_window.py
visualpic/ui/render_settings_dialog.py
visualpic/ui/save_colormap_dialog.py
visualpic/ui/save_colormap_dialog.ui
visualpic/ui/save_opacity_dialog.py
visualpic/ui/save_opacity_dialog.ui
visualpic/ui/setup_field_volume_window.py
visualpic/ui/setup_field_volume_window.ui
visualpic/ui/setup_scatter_species_dialog.py
visualpic/ui/controls/__init__.py
visualpic/ui/controls/mpl_figure_with_draggable_points.py
visualpic/ui/controls/qt/QVTKRenderWindowInteractor.py
visualpic/ui/controls/qt/__init__.py
visualpic/ui/controls/qt4/QVTKRenderWindowInteractor.py
visualpic/ui/controls/qt4/__init__.py
visualpic/ui/icons/__init__.py
visualpic/ui/icons/edit.svg
visualpic/ui/icons/left_arrow.png
visualpic/ui/icons/right_arrow.png
visualpic/ui/icons/save.svg
visualpic/ui/icons/slider_settings.svg
visualpic/ui/icons/vp_logo_horiz_transp.png
visualpic/ui/icons/vp_logo_sq.png
visualpic/ui/icons/vp_logo_sq_blue.png
visualpic/ui/icons/vp_logo_sq_blue_hires.png
visualpic/ui/icons/vp_logo_sq_dark.png
visualpic/visualization/__init__.py
visualpic/visualization/volume_appearance.py
visualpic/visualization/vtk_visualizer.py
visualpic/visualization/assets/__init__.py
VisualPIC-0.5.2.dist-info/LICENSE
VisualPIC-0.5.2.dist-info/METADATA
VisualPIC-0.5.2.dist-info/WHEEL
VisualPIC-0.5.2.dist-info/entry_points.txt
VisualPIC-0.5.2.dist-info/top_level.txt
VisualPIC-0.5.2.dist-info/RECORD
