Metadata-Version: 2.1
Name: VisualPIC
Version: 0.5.2
Summary: Data visualizer for PIC codes
Home-page: https://github.com/AngelFP/VisualPIC
Author: Angel Ferran Pousa
Author-email: angel.ferran.pousa@desy.de,
License: GPLv3
Classifier: Development Status :: 3 - Alpha
Classifier: Programming Language :: Python :: 3
Classifier: Intended Audience :: Science/Research
Classifier: Topic :: Scientific/Engineering :: Physics
Classifier: Topic :: Scientific/Engineering :: Visualization
Classifier: License :: OSI Approved :: GNU General Public License v3 (GPLv3)
Classifier: Operating System :: OS Independent
Requires-Python: >=3.7
License-File: LICENSE
Requires-Dist: numpy
Requires-Dist: scipy
Requires-Dist: h5py
Requires-Dist: matplotlib
Requires-Dist: aptools >=0.1.25
Requires-Dist: openpmd-viewer !=1.4.0,>=1.2.0
Requires-Dist: tqdm
Provides-Extra: test
Requires-Dist: pytest ; extra == 'test'
Requires-Dist: flake8 ; extra == 'test'
Requires-Dist: pyvista ; extra == 'test'
